[
    {
    "company": "AH2",
    "title": "Founder",
    "start": "May 2024",
    "end": "Current"
  },
  {
    "company": "Ollion",
    "title": "Head of Media & Entertainment Solutions",
    "start": "Mar 2022",
    "end": "May 2024"
  },
  {
    "company": "Ollion",
    "title": "Specialist Solutions Architect",
    "start": "Nov 2020",
    "end": "Mar 2022"
  },
  {
    "company": "Onica",
    "title": "Customer Solutions Architect",
    "start": "Jan 2020",
    "end": "Jun 2020"
  },
  {
    "company": "Mission",
    "title": "Senior Cloud Solutions Architect",
    "start": "Jan 2019",
    "end": "Dec 2019"
  },
  {
    "company": "General Datatech",
    "title": "Cloud Solutions Architect",
    "start": "Apr 2018",
    "end": "Jan 2019"
  },
  {
    "company": "Capgemini",
    "title": "Senior Cloud Consultant",
    "start": "Feb 2017",
    "end": "Apr 2018"
  },
  {
    "company": "Self Employed",
    "title": "Independent Web & Cloud Consultant",
    "start": "Sep 2010",
    "end": "Feb 2017"
  }
]
